push_version/__init__.py
push_version/push.py
push_app_version-0.0.5.dist-info/LICENSE
push_app_version-0.0.5.dist-info/METADATA
push_app_version-0.0.5.dist-info/WHEEL
push_app_version-0.0.5.dist-info/entry_points.txt
push_app_version-0.0.5.dist-info/top_level.txt
push_app_version-0.0.5.dist-info/RECORD
