Metadata-Version: 2.1
Name: push-app-version
Version: 0.0.5
Summary: Push version in GCS bucket for triggered deployments
Home-page: https://github.com/mrpink/push-app-version
Author: Will Pink
Author-email: UNKNOWN
License: UNKNOWN
Keywords: google gcs version
Platform: UNKNOWN
Requires-Dist: google-cloud-storage
